documenso_sdk/__init__.py
documenso_sdk/_hooks/__init__.py
documenso_sdk/_hooks/registration.py
documenso_sdk/_hooks/sdkhooks.py
documenso_sdk/_hooks/types.py
documenso_sdk/_version.py
documenso_sdk/basesdk.py
documenso_sdk/directlink_sdk.py
documenso_sdk/document_sdk.py
documenso_sdk/documents.py
documenso_sdk/documents_attachments.py
documenso_sdk/documents_fields.py
documenso_sdk/documents_recipients.py
documenso_sdk/embedding.py
documenso_sdk/envelopes.py
documenso_sdk/envelopes_attachments.py
documenso_sdk/envelopes_fields.py
documenso_sdk/envelopes_recipients.py
documenso_sdk/folders.py
documenso_sdk/httpclient.py
documenso_sdk/items.py
documenso_sdk/models/__init__.py
documenso_sdk/models/apierror.py
documenso_sdk/models/documensoerror.py
documenso_sdk/models/document_attachment_createop.py
documenso_sdk/models/document_attachment_deleteop.py
documenso_sdk/models/document_attachment_findop.py
documenso_sdk/models/document_attachment_updateop.py
documenso_sdk/models/document_createdocumenttemporaryop.py
documenso_sdk/models/document_createop.py
documenso_sdk/models/document_deleteop.py
documenso_sdk/models/document_distributeop.py
documenso_sdk/models/document_downloadbetaop.py
documenso_sdk/models/document_downloadop.py
documenso_sdk/models/document_duplicateop.py
documenso_sdk/models/document_findop.py
documenso_sdk/models/document_getop.py
documenso_sdk/models/document_redistributeop.py
documenso_sdk/models/document_updateop.py
documenso_sdk/models/embeddingpresign_createembeddingpresigntokenop.py
documenso_sdk/models/embeddingpresign_verifyembeddingpresigntokenop.py
documenso_sdk/models/envelope_attachment_createop.py
documenso_sdk/models/envelope_attachment_deleteop.py
documenso_sdk/models/envelope_attachment_findop.py
documenso_sdk/models/envelope_attachment_updateop.py
documenso_sdk/models/envelope_createop.py
documenso_sdk/models/envelope_deleteop.py
documenso_sdk/models/envelope_distributeop.py
documenso_sdk/models/envelope_duplicateop.py
documenso_sdk-0.4.0.dist-info/METADATA
documenso_sdk-0.4.0.dist-info/WHEEL
documenso_sdk-0.4.0.dist-info/licenses/LICENSE
documenso_sdk-0.4.0.dist-info/RECORD
